Workbook

Sheet Sheet1
F1: Last Twelve Month (LTM) | K1: Year 1 Forecast - Calendar Year | P1: Year 2 Forecast Calendar Year
A2: NAME | B2: Ticker | C2: Market Capitalization(mm) | D2: Enterperise value | F2: Revenues | G2: EBITDA | H2: EBIT | I2: EPS | K2: Revenues | L2: EBITDA | M2: EBIT | N2: EPS | P2: Revenues | Q2: EBITDA | R2: EBIT | S2: EPS | T2: LT Growth rate | V2: Net Debt | W2: Diluted Shares Outstanding
A4: #VALUE! | B4: WMT | C4: 447310 | D4: 504226 | F4: 630794 | G4: 37112 | H4: 25796 | I4: 6.52 | K4: =(639815+653268)/2 -> 646541.5 | L4: =(38463+39487)/2 -> 38975 | M4: =(26727+27566)/2 -> 27146.5 | N4: =(6.5+6.79)/2 -> 6.645 | P4: =(662291+676563)/2 -> 669427 | Q4: =(41066+41464)/2 -> 41265 | R4: =(28764+29238)/2 -> 29001 | S4: =(7.13+7.43)/2 -> 7.28 | T4: ='[1]Analysis Output'!T9 -> 0.0468 | V4: =64801-13888 -> 50913 | W4: 2691
A5: #VALUE! | B5: TGT | C5: 50005 | D5: 67218 | F5: 108008 | G5: 7491 | H5: 4770 | I5: 7.28 | K5: =(106979+107588)/2 -> 107283.5 | L5: =(7671+8076)/2 -> 7873.5 | M5: =(4976+5419)/2 -> 5197.5 | N5: =(7.56+8.31)/2 -> 7.935 | P5: =(107475+108615)/2 -> 108045 | Q5: =(8480+8566)/2 -> 8523 | R5: =(5748+5894)/2 -> 5821 | S5: =(8.85+9.25)/2 -> 9.05 | T5: ='[1]Analysis Output'!T10 -> 0.1272 | V5: =18830-1617 -> 17213 | W5: 462
A6: #VALUE! | B6: COST | C6: 255514 | D6: 249164 | F6: 242900 | G6: 10254 | H6: 8177 | I6: 14.16 | K6: =(253037+253913)/2 -> 253475 | L6: =(11320+11323)/2 -> 11321.5 | M6: =(8993+9018)/2 -> 9005.5 | N6: =(15.67+15.64)/2 -> 15.655 | P6: =(269966+271059)/2 -> 270512.5 | Q6: =(12354+12383)/2 -> 12368.5 | R6: =(9850+9884)/2 -> 9867 | S6: =(17.17+17.1)/2 -> 17.135 | T6: ='[1]Analysis Output'!T11 -> 0.1243 | V6: =8884-15234 -> -6350 | W6: 443
A7: #VALUE! | B7: AMZN | C7: 1483553 | D7: 1556373 | F7: 538046 | G7: 61868 | H7: 14257 | I7: 1.39 | K7: =(635789+598711)/2 -> 617250 | L7: =(124757+111540)/2 -> 118148.5 | M7: =(44469+37244)/2 -> 40856.5 | N7: =(3.42+2.86)/2 -> 3.14 | P7: =(709443+669364)/2 -> 689403.5 | Q7: =(145920+133299)/2 -> 139609.5 | R7: =(59323+52491)/2 -> 55907 | S7: =(4.64+3.92)/2 -> 4.28 | T7: ='[1]Analysis Output'!T12 -> 0.0636 | V7: =136989-64169 -> 72820 | W7: 10334
A8: #VALUE! | B8: CVS | C8: 87097 | D8: 151178 | F8: 339204 | G8: 19633 | H8: 17167 | I8: 8.57 | K8: =(348990+345275)/2 -> 347132.5 | L8: =(19226+19951)/2 -> 19588.5 | M8: =(17190+17263)/2 -> 17226.5 | N8: =(8.4+8.57)/2 -> 8.485 | P8: =(355229+363510)/2 -> 359369.5 | Q8: =(19967+20837)/2 -> 20402 | R8: =(17825+18308)/2 -> 18066.5 | S8: =(9.01+9.4)/2 -> 9.205 | T8: ='[1]Analysis Output'!T13 -> 0.0997 | V8: =80096-16188 -> 63908 | W8: 1287
A9: #VALUE! | B9: KR | C9: 31570 | D9: 47816 | F9: 148038 | G9: 8424 | H9: 4744 | I9: 4.27 | K9: =(150821+150066)/2 -> 150443.5 | L9: =(7874+7888)/2 -> 7881 | M9: =(4713+4757)/2 -> 4735 | N9: =(4.54+4.53)/2 -> 4.535 | P9: =(149852+150069)/2 -> 149960.5 | Q9: =(7843+7766)/2 -> 7804.5 | R9: =(4666+4607)/2 -> 4636.5 | S9: =(4.42+4.47)/2 -> 4.445 | T9: ='[1]Analysis Output'!T14 -> 0.2826 | V9: =19829-3561 -> 16268 | W9: 719
A15: NAME | B15: Ticker | F15: Last Twelve Month (LTM) | K15: Year 1 Forecast Calendar Year | P15: Year 2 Forecast Calendar Year
F16: EV/ Revenues | G16: EV/EBIDTA | H16: EV/EBIT | I16: P/E | K16: EV/ Revenues | L16: EV/EBIDTA | M16: EV/EBIT | N16: P/E | P16: EV/ Revenues | Q16: EV/EBIDTA | R16: EV/EBIT | S16: P/E | T16: PEG Ratio
A18: #VALUE! | B18: WMT | F18: =D4/F4 -> 0.79935129 | G18: =D4/G4 -> 13.586603 | H18: =D4/H4 -> 19.546674 | I18: {=_FV(A4,"P/E",TRUE)} -> 45.6978 | K18: =D4/K4 -> 0.77988188 | L18: =D4/L4 -> 12.937165 | M18: =D4/M4 -> 18.574255 | N18: =I37/N4 -> 44.838172 | P18: =D4/P4 -> 0.75322029 | Q18: =D4/Q4 -> 12.219217 | R18: =D4/R4 -> 17.386504 | S18: =I37/S4 -> 40.927151 | T18: =(S18/T4)/100 -> 8.7451176
A19: #VALUE! | B19: TGT | F19: =D5/F5 -> 0.62234279 | G19: =D5/G5 -> 8.9731678 | H19: =D5/H5 -> 14.091824 | I19: {=_FV(A5,"P/E",TRUE)} -> 14.6154 | K19: =D5/K5 -> 0.62654555 | L19: =D5/L5 -> 8.5372452 | M19: =D5/M5 -> 12.932756 | N19: =I38/N5 -> 13.408962 | P19: =D5/P5 -> 0.62212967 | Q19: =D5/Q5 -> 7.8866596 | R19: =D5/R5 -> 11.5475 | S19: =I38/S5 -> 11.756918 | T19: =(S19/T5)/100 -> 0.92428604
A20: #VALUE! | B20: COST | F20: =D6/F6 -> 1.0257884 | G20: =D6/G6 -> 24.2992 | H20: =D6/H6 -> 30.471322 | I20: {=_FV(A6,"P/E",TRUE)} -> 53.3829 | K20: =D6/K6 -> 0.98299241 | L20: =D6/L6 -> 22.008038 | M20: =D6/M6 -> 27.667981 | N20: =I39/N6 -> 48.285012 | P20: =D6/P6 -> 0.92108128 | Q20: =D6/Q6 -> 20.145046 | R20: =D6/R6 -> 25.252255 | S20: =I39/S6 -> 44.114495 | T20: =(S20/T6)/100 -> 3.5490342
A21: #VALUE! | B21: AMZN | F21: =D7/F7 -> 2.8926393 | G21: =D7/G7 -> 25.156349 | H21: =D7/H7 -> 109.16553 | I21: {=_FV(A7,"P/E",TRUE)} -> 29.359 | K21: =D7/K7 -> 2.5214629 | L21: =D7/L7 -> 13.173024 | M21: =D7/M7 -> 38.093645 | N21: =I40/N7 -> 12.9965 | P21: =D7/P7 -> 2.2575647 | Q21: =D7/Q7 -> 11.148045 | R21: =D7/R7 -> 27.838607 | S21: =I40/S7 -> 9.5348154 | T21: =(S21/T7)/100 -> 1.4991848
A22: #VALUE! | B22: CVS | F22: =D8/F8 -> 0.4456846 | G22: =D8/G8 -> 7.7001986 | H22: =D8/H8 -> 8.8063144 | I22: {=_FV(A8,"P/E",TRUE)} -> 53.0099 | K22: =D8/K8 -> 0.43550517 | L22: =D8/L8 -> 7.7176915 | M22: =D8/M8 -> 8.7758976 | N22: =I41/N8 -> 53.540936 | P22: =D8/P8 -> 0.42067566 | Q22: =D8/Q8 -> 7.4099598 | R22: =D8/R8 -> 8.3678632 | S22: =I41/S8 -> 49.353052 | T22: =(S22/T8)/100 -> 4.9501557
A23: #VALUE! | B23: KR | F23: =D9/F9 -> 0.32299815 | G23: =D9/G9 -> 5.6761633 | H23: =D9/H9 -> 10.079258 | I23: {=_FV(A9,"P/E",TRUE)} -> 64.6071 | K23: =D9/K9 -> 0.31783361 | L23: =D9/L9 -> 6.0672503 | M23: =D9/M9 -> 10.098416 | N23: =I42/N9 -> 60.831823 | P23: =D9/P9 -> 0.3188573 | Q23: =D9/Q9 -> 6.1267218 | R23: =D9/R9 -> 10.312952 | S23: =I42/S9 -> 62.063513 | T23: =(S23/T9)/100 -> 2.1961611
C27: High | F27: =F21 -> 2.8926393 | G27: =G21 -> 25.156349 | H27: =H21 -> 109.16553 | I27: =I21 -> 29.359 | K27: =K21 -> 2.5214629 | L27: =L20 -> 22.008038 | M27: =M21 -> 38.093645 | N27: =N21 -> 12.9965 | P27: =P21 -> 2.2575647 | Q27: =Q20 -> 20.145046 | R27: =R21 -> 27.838607 | S27: =S20 -> 44.114495
C28: Low | F28: =F23 -> 0.32299815 | G28: =G23 -> 5.6761633 | H28: =H22 -> 8.8063144 | I28: =I22 -> 53.0099 | K28: =K23 -> 0.31783361 | L28: =L23 -> 6.0672503 | M28: =M22 -> 8.7758976 | N28: =N22 -> 53.540936 | P28: =P23 -> 0.3188573 | Q28: =Q23 -> 6.1267218 | R28: =R22 -> 8.3678632 | S28: =S22 -> 49.353052
C29: Median | F29: =MEDIAN(F18:F23) -> 0.71084704 | G29: =MEDIAN(G18:G23) -> 11.279885 | H29: =MEDIAN(H18:H23) -> 16.819249 | I29: =MEDIAN(I18:I23) -> 49.35385 | K29: =MEDIAN(K18:K23) -> 0.70321372 | L29: =MEDIAN(L18:L23) -> 10.737205 | M29: =MEDIAN(M18:M23) -> 15.753505 | N29: =MEDIAN(N18:N23) -> 46.561592 | P29: =MEDIAN(P18:P23) -> 0.68767498 | Q29: =MEDIAN(Q18:Q23) -> 9.5173524 | R29: =MEDIAN(R18:R23) -> 14.467002 | S29: =MEDIAN(S18:S23) -> 42.520823
C30: Mean | F30: =AVERAGE(F18:F23) -> 1.0181341 | G30: =AVERAGE(G18:G23) -> 14.231947 | H30: =AVERAGE(H18:H23) -> 32.026821 | I30: =AVERAGE(I18:I23) -> 43.44535 | K30: =AVERAGE(K18:K23) -> 0.94403693 | L30: =AVERAGE(L18:L23) -> 11.740069 | M30: =AVERAGE(M18:M23) -> 19.357158 | N30: =AVERAGE(N18:N23) -> 38.983568 | P30: =AVERAGE(P18:P23) -> 0.88225481 | Q30: =AVERAGE(Q18:Q23) -> 10.822608 | R30: =AVERAGE(R18:R23) -> 16.78428 | S30: =AVERAGE(S18:S23) -> 36.291657
C31: Mean( excl WMT) | F31: =AVERAGE(F19:F23) -> 1.0618906 | G31: =AVERAGE(G19:G23) -> 14.361016 | H31: =AVERAGE(H19:H23) -> 34.52285 | I31: =AVERAGE(I19:I23) -> 42.99486 | K31: =AVERAGE(K19:K23) -> 0.97686794 | L31: =AVERAGE(L19:L23) -> 11.50065 | M31: =AVERAGE(M19:M23) -> 19.513739 | N31: =AVERAGE(N19:N23) -> 37.812647 | P31: =AVERAGE(P19:P23) -> 0.90806172 | Q31: =AVERAGE(Q19:Q23) -> 10.543286 | R31: =AVERAGE(R19:R23) -> 16.663835 | S31: =AVERAGE(S19:S23) -> 35.364559
C33: WMT | F33: =F18 -> 0.79935129 | G33: =G18 -> 13.586603 | H33: =H18 -> 19.546674 | I33: =I18 -> 45.6978 | K33: =K18 -> 0.77988188 | L33: =L18 -> 12.937165 | M33: =M18 -> 18.574255 | N33: =N18 -> 44.838172 | P33: =P18 -> 0.75322029 | Q33: =Q18 -> 12.219217 | R33: =R18 -> 17.386504 | S33: =S18 -> 40.927151
W36: =2.7*587824 -> 1587124.8
A37: 8.32 - | F37: Current price | I37: =I18*I4 -> 297.94966
A38: 33.65- | I38: =I19*I5 -> 106.40011
A39: 50.49 | I39: =I20*I6 -> 755.90186
A40: 12.51 | I40: =I21*I7 -> 40.80901
A41: 33.91- | I41: =I22*I8 -> 454.29484
I42: =I23*I9 -> 275.87232

Sheet Sheet2
B1: Last Twelve Month (LTM) | G1: Year 1 Forecast Calendar Year | L1: Year 2 Forecast Calendar Year
B2: EV/ Revenues | C2: EV/EBIDTA | D2: EV/EBIT | E2: P/E | G2: EV/ Revenues | H2: EV/EBIDTA | I2: EV/EBIT | J2: P/E | L2: EV/ Revenues | M2: EV/EBIDTA | N2: EV/EBIT | O2: P/E
A4: High | B4: =Sheet1!F27 -> 2.8926393 | C4: =Sheet1!G27 -> 25.156349 | D4: =Sheet1!H27 -> 109.16553 | E4: =Sheet1!I27 -> 29.359 | G4: =Sheet1!K27 -> 2.5214629 | H4: =Sheet1!L27 -> 22.008038 | I4: =Sheet1!M27 -> 38.093645 | J4: =Sheet1!N27 -> 12.9965 | L4: =Sheet1!P27 -> 2.2575647 | M4: =Sheet1!Q27 -> 20.145046 | N4: =Sheet1!R27 -> 27.838607 | O4: =Sheet1!S27 -> 44.114495
A5: Low | B5: =Sheet1!F28 -> 0.32299815 | C5: =Sheet1!G28 -> 5.6761633 | D5: =Sheet1!H28 -> 8.8063144 | E5: =Sheet1!I28 -> 53.0099 | G5: =Sheet1!K28 -> 0.31783361 | H5: =Sheet1!L28 -> 6.0672503 | I5: =Sheet1!M28 -> 8.7758976 | J5: =Sheet1!N28 -> 53.540936 | L5: =Sheet1!P28 -> 0.3188573 | M5: =Sheet1!Q28 -> 6.1267218 | N5: =Sheet1!R28 -> 8.3678632 | O5: =Sheet1!S28 -> 49.353052
A6: Median | B6: =Sheet1!F29 -> 0.71084704 | C6: =Sheet1!G29 -> 11.279885 | D6: =Sheet1!H29 -> 16.819249 | E6: =Sheet1!I29 -> 49.35385 | G6: =Sheet1!K29 -> 0.70321372 | H6: =Sheet1!L29 -> 10.737205 | I6: =Sheet1!M29 -> 15.753505 | J6: =Sheet1!N29 -> 46.561592 | L6: =Sheet1!P29 -> 0.68767498 | M6: =Sheet1!Q29 -> 9.5173524 | N6: =Sheet1!R29 -> 14.467002 | O6: =Sheet1!S29 -> 42.520823
A9: Comps- Derived WMT Value
A11: High
A12: Enterprise value | B12: =B4*Sheet1!F4 -> 1824659.5 | C12: =C4*Sheet1!G4 -> 933602.42 | D12: =D4*Sheet1!H4 -> 2816034.1 | E12: =E13+E14 -> 566026.05 | G12: =G4*Sheet1!K4 -> 1630230.4 | H12: =H4*Sheet1!L4 -> 857763.27 | I12: =I4*Sheet1!M4 -> 1034109.1 | J12: =J14+J13 -> 283312.45 | L12: =L4*Sheet1!P4 -> 1511274.8 | M12: =M4*Sheet1!Q4 -> 831285.32 | N12: =N4*Sheet1!R4 -> 807347.44 | O12: =O14+O13 -> 915137.12
A13: Net Debt | B13: =Sheet1!V4 -> 50913 | C13: =Sheet1!$V$4 -> 50913 | D13: =Sheet1!$V$4 -> 50913 | E13: =Sheet1!$V$4 -> 50913 | G13: =Sheet1!$V$4 -> 50913 | H13: =Sheet1!$V$4 -> 50913 | I13: =Sheet1!$V$4 -> 50913 | J13: =Sheet1!$V$4 -> 50913 | L13: =Sheet1!$V$4 -> 50913 | M13: =Sheet1!$V$4 -> 50913 | N13: =Sheet1!$V$4 -> 50913 | O13: =Sheet1!$V$4 -> 50913
A14: Equity Value | B14: =B12-B13 -> 1773746.5 | C14: =C12-C13 -> 882689.42 | D14: =D12-D13 -> 2765121.1 | E14: =E15*E16 -> 515113.05 | G14: =G12-G13 -> 1579317.4 | H14: =H12-H13 -> 806850.27 | I14: =I12-I13 -> 983196.13 | J14: =J15*J16 -> 232399.45 | L14: =L12-L13 -> 1460361.8 | M14: =M12-M13 -> 780372.32 | N14: =N12-N13 -> 756434.44 | O14: =O15*O16 -> 864224.12
A15: Shares Outstanding | B15: =Sheet1!$W$4 -> 2691 | C15: =Sheet1!$W$4 -> 2691 | D15: =Sheet1!$W$4 -> 2691 | E15: =Sheet1!$W$4 -> 2691 | G15: =Sheet1!$W$4 -> 2691 | H15: =Sheet1!$W$4 -> 2691 | I15: =Sheet1!$W$4 -> 2691 | J15: =Sheet1!$W$4 -> 2691 | L15: =Sheet1!$W$4 -> 2691 | M15: =Sheet1!$W$4 -> 2691 | N15: =Sheet1!$W$4 -> 2691 | O15: =Sheet1!$W$4 -> 2691
A16: Shares Price | B16: =B14/B15 -> 659.14029 | C16: =C14/C15 -> 328.01539 | D16: =D14/D15 -> 1027.5441 | E16: =E4*Sheet1!I4 -> 191.42068 | G16: =G14/G15 -> 586.88868 | H16: =H14/H15 -> 299.83288 | I16: =I14/I15 -> 365.3646 | J16: =J4*Sheet1!N4 -> 86.361743 | L16: =L14/L15 -> 542.68367 | M16: =M14/M15 -> 289.99343 | N16: =N14/N15 -> 281.0979 | O16: =O4*Sheet1!S4 -> 321.15352
A18: Low
A19: Enterprise value | B19: =B5*Sheet1!F4 -> 203745.29 | C19: =C5*Sheet1!G4 -> 210653.77 | D19: =D5*Sheet1!H4 -> 227167.69 | E19: =E20+E21 -> 980988.66 | G19: =G5*Sheet1!K4 -> 205492.62 | H19: =H5*Sheet1!L4 -> 236471.08 | I19: =I5*Sheet1!M4 -> 238234.9 | J19: =J20+J21 -> 1008315.7 | L19: =L5*Sheet1!P4 -> 213451.69 | M19: =M5*Sheet1!Q4 -> 252819.17 | N19: =N5*Sheet1!R4 -> 242676.4 | O19: =O21+O20 -> 1017763
A20: Net Debt | B20: =Sheet1!$V$4 -> 50913 | C20: =Sheet1!$V$4 -> 50913 | D20: =Sheet1!$V$4 -> 50913 | E20: =Sheet1!$V$4 -> 50913 | G20: =Sheet1!$V$4 -> 50913 | H20: =Sheet1!$V$4 -> 50913 | I20: =Sheet1!$V$4 -> 50913 | J20: =Sheet1!$V$4 -> 50913 | L20: =Sheet1!$V$4 -> 50913 | M20: =Sheet1!$V$4 -> 50913 | N20: =Sheet1!$V$4 -> 50913 | O20: =Sheet1!$V$4 -> 50913
A21: Equity Value | B21: =B19-B20 -> 152832.29 | C21: =C19-C20 -> 159740.77 | D21: =D19-D20 -> 176254.69 | E21: =E22*E23 -> 930075.66 | G21: =G19-G20 -> 154579.62 | H21: =H19-H20 -> 185558.08 | I21: =I19-I20 -> 187321.9 | J21: =J23*J22 -> 957402.69 | L21: =L19-L20 -> 162538.69 | M21: =M19-M20 -> 201906.17 | N21: =N19-N20 -> 191763.4 | O21: =O23*O22 -> 966849.98
A22: Shares Outstanding | B22: =Sheet1!$W$4 -> 2691 | C22: =Sheet1!$W$4 -> 2691 | D22: =Sheet1!$W$4 -> 2691 | E22: =Sheet1!$W$4 -> 2691 | G22: =Sheet1!$W$4 -> 2691 | H22: =Sheet1!$W$4 -> 2691 | I22: =Sheet1!$W$4 -> 2691 | J22: =Sheet1!$W$4 -> 2691 | L22: =Sheet1!$W$4 -> 2691 | M22: =Sheet1!$W$4 -> 2691 | N22: =Sheet1!$W$4 -> 2691 | O22: =Sheet1!$W$4 -> 2691
A23: Shares Price | B23: =B21/B22 -> 56.793866 | C23: =C21/C22 -> 59.36112 | D23: =D21/D22 -> 65.49784 | E23: =E5*Sheet1!I4 -> 345.62455 | G23: =G21/G22 -> 57.443187 | H23: =H21/H22 -> 68.955066 | I23: =I21/I22 -> 69.610518 | J23: =J5*Sheet1!N4 -> 355.77952 | L23: =L21/L22 -> 60.400849 | M23: =M21/M22 -> 75.030165 | N23: =N21/N22 -> 71.261018 | O23: =O5*Sheet1!S4 -> 359.29022
A25: Median
A26: Enterprise value | B26: =B6*Sheet1!F4 -> 448398.05 | C26: =C6*Sheet1!G4 -> 418619.1 | D26: =D6*Sheet1!H4 -> 433869.34 | E26: =E28+E27 -> 916842.09 | G26: =G6*Sheet1!K4 -> 454656.85 | H26: =H6*Sheet1!L4 -> 418482.57 | I26: =I6*Sheet1!M4 -> 427652.53 | J26: =J27+J28 -> 963076.94 | L26: =L6*Sheet1!P4 -> 460348.2 | M26: =M6*Sheet1!Q4 -> 392733.54 | N26: =N6*Sheet1!R4 -> 419557.53 | O26: =O27+O28 -> 883916.32
A27: Net Debt | B27: =Sheet1!$V$4 -> 50913 | C27: =Sheet1!$V$4 -> 50913 | D27: =Sheet1!$V$4 -> 50913 | E27: =Sheet1!$V$4 -> 50913 | G27: =Sheet1!$V$4 -> 50913 | H27: =Sheet1!$V$4 -> 50913 | I27: =Sheet1!$V$4 -> 50913 | J27: =Sheet1!$V$4 -> 50913 | L27: =Sheet1!$V$4 -> 50913 | M27: =Sheet1!$V$4 -> 50913 | N27: =Sheet1!$V$4 -> 50913 | O27: =Sheet1!$V$4 -> 50913
A28: Equity Value | B28: =B26-B27 -> 397485.05 | C28: =C26-C27 -> 367706.1 | D28: =D26-D27 -> 382956.34 | E28: =E29*E30 -> 865929.09 | G28: =G26-G27 -> 403743.85 | H28: =H26-H27 -> 367569.57 | I28: =I26-I27 -> 376739.53 | J28: =J30*J29 -> 912163.94 | L28: =L26-L27 -> 409435.2 | M28: =M26-M27 -> 341820.54 | N28: =N26-N27 -> 368644.53 | O28: =O30*O29 -> 833003.32
A29: Shares Outstanding | B29: =Sheet1!$W$4 -> 2691 | C29: =Sheet1!$W$4 -> 2691 | D29: =Sheet1!$W$4 -> 2691 | E29: =Sheet1!$W$4 -> 2691 | G29: =Sheet1!$W$4 -> 2691 | H29: =Sheet1!$W$4 -> 2691 | I29: =Sheet1!$W$4 -> 2691 | J29: =Sheet1!$W$4 -> 2691 | L29: =Sheet1!$W$4 -> 2691 | M29: =Sheet1!$W$4 -> 2691 | N29: =Sheet1!$W$4 -> 2691 | O29: =Sheet1!$W$4 -> 2691
A30: Shares Price | B30: =B28/B29 -> 147.70905 | C30: =C28/C29 -> 136.64292 | D30: =D28/D29 -> 142.31005 | E30: =E6*Sheet1!I4 -> 321.7871 | G30: =G28/G29 -> 150.03488 | H30: =H28/H29 -> 136.59218 | I30: =I28/I29 -> 139.99983 | J30: =J6*Sheet1!S4 -> 338.96839 | L30: =L28/L29 -> 152.14983 | M30: =M28/M29 -> 127.02361 | N30: =N28/N29 -> 136.99165 | O30: =O6*Sheet1!S4 -> 309.55159
A33: Enterprise value
A34: Net Debt | B34: =Sheet1!$V$4 -> 50913 | C34: =Sheet1!$V$4 -> 50913 | D34: =Sheet1!$V$4 -> 50913 | E34: =Sheet1!$V$4 -> 50913 | G34: =Sheet1!$V$4 -> 50913 | H34: =Sheet1!$V$4 -> 50913 | I34: =Sheet1!$V$4 -> 50913 | J34: =Sheet1!$V$4 -> 50913 | L34: =Sheet1!$V$4 -> 50913 | M34: =Sheet1!$V$4 -> 50913 | N34: =Sheet1!$V$4 -> 50913 | O34: =Sheet1!$V$4 -> 50913
A35: Equity Value | B35: =B33-B34 -> -50913 | C35: =C33-C34 -> -50913 | D35: =D33-D34 -> -50913 | E35: =E33-E34 -> -50913 | G35: =G33-G34 -> -50913 | H35: =H33-H34 -> -50913 | I35: =I33-I34 -> -50913 | J35: =J33-J34 -> -50913 | L35: =L33-L34 -> -50913 | M35: =M33-M34 -> -50913 | N35: =N33-N34 -> -50913 | O35: =O33-O34 -> -50913
A36: Shares Outstanding | B36: =Sheet1!$W$4 -> 2691 | C36: =Sheet1!$W$4 -> 2691 | D36: =Sheet1!$W$4 -> 2691 | E36: =Sheet1!$W$4 -> 2691 | G36: =Sheet1!$W$4 -> 2691 | H36: =Sheet1!$W$4 -> 2691 | I36: =Sheet1!$W$4 -> 2691 | J36: =Sheet1!$W$4 -> 2691 | L36: =Sheet1!$W$4 -> 2691 | M36: =Sheet1!$W$4 -> 2691 | N36: =Sheet1!$W$4 -> 2691 | O36: =Sheet1!$W$4 -> 2691
A37: Shares Price | B37: =B35/B36 -> -18.919732 | C37: =C35/C36 -> -18.919732 | D37: =D35/D36 -> -18.919732 | E37: =E35/E36 -> -18.919732 | G37: =G35/G36 -> -18.919732 | H37: =H35/H36 -> -18.919732 | I37: =I35/I36 -> -18.919732 | J37: =J35/J36 -> -18.919732 | L37: =L35/L36 -> -18.919732 | M37: =M35/M36 -> -18.919732 | N37: =N35/N36 -> -18.919732 | O37: =O35/O36 -> -18.919732
E46: f

Sheet Sheet3
A1: Walmart Value Range Table
A2: Methodology | B2: Lower Value | C2: Upper Value | D2: Median Value
A3: 1 YR EV/EBIT | B3: =MIN(Sheet2!I16,Sheet2!N16,Sheet2!I23,Sheet2!N23,Sheet2!I30,Sheet2!N30) -> 69.610518 | C3: =MAX(Sheet2!I16,Sheet2!N16,Sheet2!I23,Sheet2!N23,Sheet2!I30,Sheet2!N30) -> 365.3646 | D3: =Sheet2!I30 -> 139.99983
A4: LTM EV / EBITDA | B4: =MIN(Sheet2!C16,Sheet2!C23,Sheet2!C30) -> 59.36112 | C4: =MAX(Sheet2!C16,Sheet2!C23,Sheet2!C30) -> 328.01539 | D4: =Sheet2!C30 -> 136.64292
A5: LTM EV / EBIT | B5: =MIN(Sheet2!D16,Sheet2!D23,Sheet2!D30) -> 65.49784 | C5: =MAX(Sheet2!D16,Sheet2!D23,Sheet2!D30) -> 1027.5441 | D5: =Sheet2!D30 -> 142.31005
A6: LTM P/E | B6: =MIN(Sheet2!E16,Sheet2!E23,Sheet2!E30) -> 191.42068 | C6: =MAX(Sheet2!E16,Sheet2!E23,Sheet2!E30) -> 345.62455 | D6: =Sheet2!E30 -> 321.7871
A7: 1 YR P/E | B7: =MIN(Sheet2!J16,Sheet2!J23,Sheet2!J30,Sheet2!O16,Sheet2!O23,Sheet2!O30) -> 86.361743 | C7: =MAX(Sheet2!J16,Sheet2!J23,Sheet2!J30,Sheet2!O16,Sheet2!O23,Sheet2!O30) -> 359.29022 | D7: =Sheet2!J30 -> 338.96839
A9: Walmart Price (52 Week Range)
A10: Median Range | B10: =MIN(D3:D7) -> 136.64292 | C10: =MAX(D3:D7) -> 338.96839 | D10: =(B10+C10)/2 -> 237.80566
B15: =AVERAGE(B3:B7) -> 94.45038 | C15: =AVERAGE(C3:C7) -> 485.16776 | D15: =AVERAGE(D3:D7) -> 215.94166 | E15: =B15+C15+D15 -> 795.5598
D16: =(D10+E16)/2 -> 251.49613 | E16: =E15/3 -> 265.1866
D17: =D16+153 -> 404.49613 | E17: =D17/2 -> 202.24806
